{
    "id": "13v0tkm",
    "score": 9,
    "title": "mattress topper",
    "author": "Lanky-Paper414",
    "date": 1685380714.0,
    "url": "https://www.reddit.com/r/UPenn/comments/13v0tkm",
    "media_urls": [],
    "other_urls": [],
    "postText": "hi im am incoming freshman and im looking to buy a mattress topper. should i buy a memory foam topper or a down alternative one?",
    "comments": [
        {
            "level": 0,
            "comment": "Memory foam, easier to maintain in Philly humidity and move between dorms since you can compress it",
            "score": 20,
            "author": "Microsoft3dgy",
            "replies": [
                {
                    "level": 1,
                    "comment": "Also came to say memory foam! It'll last longer and withstand more.",
                    "score": 9,
                    "author": "Tough_Strawberry5519"
                }
            ]
        },
        {
            "level": 0,
            "comment": "Maybe an unpopular opinion: wait and see if you actually want/need any topper at all. It's extra bulk to pack, and memory foam retains heat like a motherfucker.",
            "score": 7,
            "author": "toxic-miasma"
        }
    ]
}