{
    "id": "12gvatq",
    "score": 121,
    "title": "Dancing Light Caustics, made in Blender",
    "author": "MCPE_Master_Builder",
    "date": 1681073381.0,
    "url": "https://www.reddit.com/r/woahdude/comments/12gvatq",
    "media_urls": [
        "https://v.redd.it/u3uf2zua8xsa1"
    ],
    "other_urls": [],
    "postText": "",
    "comments": [
        {
            "level": 0,
            "comment": "Welcome to /r/WoahDude! \n\n* Check out what counts as \"woahdude material\" in our [**wiki**](https://www.reddit.com/r/woahdude/wiki/index#wiki_woahdude_material).\n\n\n*I am a bot, and this action was performed automatically. Please [contact the moderators of this subreddit](/message/compose/?to=/r/woahdude) if you have any questions or concerns.*",
            "score": 1,
            "author": "AutoModerator"
        },
        {
            "level": 0,
            "comment": "Oh my gosh, this is phenomenal work.",
            "score": 3,
            "author": "QI_haus",
            "replies": [
                {
                    "level": 1,
                    "comment": "Thank you very much! \ud83e\udd70",
                    "score": 1,
                    "author": "MCPE_Master_Builder"
                }
            ]
        }
    ]
}