{
    "id": "13w0p39",
    "score": 25,
    "title": "Best animated fights",
    "author": "travisb145",
    "date": 1685477433.0,
    "url": "https://www.reddit.com/r/animedubs/comments/13w0p39",
    "media_urls": [],
    "other_urls": [],
    "postText": "I was watching the episode of Black Clover where Yuno fights Rill in the Royal Knights tournament and I couldn\u2019t help but notice how amazing it looked. It got me thinking what are some of the best looking fights you\u2019ve seen in anime?",
    "comments": [
        {
            "level": 0,
            "comment": "One Punch Man is full of great fights, but the Genos fights are all insanely epic.\n\nAttack on Titan again has some insanely good fights, but Levi vs Beast Titan has to be my favorite.",
            "score": 20,
            "author": "weeberific",
            "replies": [
                {
                    "level": 1,
                    "comment": "MY SOLDIERS RAGEEEEEEE",
                    "score": 10,
                    "author": "East-Travel984"
                }
            ]
        },
        {
            "level": 0,
            "comment": "Either the first fight between Shinra vs his brother in Fire Force OR the Mogami battle in Mob Psycho 100. Both come to mind immediately but I\u2019ll probably have to watch them again to verify the badassery lmao",
            "score": 12,
            "author": "sock_nsych",
            "replies": [
                {
                    "level": 1,
                    "comment": "That fight from fire force is one of my favorites. Also first one to come to mind.",
                    "score": 3,
                    "author": "ElectricalTone9843"
                }
            ]
        },
        {
            "level": 0,
            "comment": "Demon Slayer, especially Tengen vs. Gyutaro gave me chills",
            "score": 21,
            "author": "VanillaDaiquiri",
            "replies": [
                {
                    "level": 1,
                    "comment": "Pretty much all of Demon Slayer Season 2 is just one big masterclass in animators having ZERO brakes.",
                    "score": 7,
                    "author": "88Dubs"
                },
                {
                    "level": 1,
                    "comment": "That\u2019s my pump up video. Gets the coin purse jingling.",
                    "score": 2,
                    "author": "AmericanRailgun"
                }
            ]
        },
        {
            "level": 0,
            "comment": "Cowboy bebop Knockin' on heaven's door has a great ending fight imo",
            "score": 8,
            "author": "CipherDaBanana"
        },
        {
            "level": 0,
            "comment": "I\u2019m surprised nobody has mentioned Saitama vs Boros from One Punch Man.",
            "score": 7,
            "author": "Oasis_951"
        },
        {
            "level": 0,
            "comment": "Anything UFOTABLE. Fate, Demon Slayer, all of their work tends to be gorgeous and fun.",
            "score": 16,
            "author": "Prophet92"
        },
        {
            "level": 0,
            "comment": "Shiro vs Gilgamesh in Fate/stay night Unlimited Blade Works.",
            "score": 5,
            "author": "Darwin343"
        },
        {
            "level": 0,
            "comment": "hunter x hunter meruem vs netero \ud83d\udd25 \ud83d\udd25 \ud83d\udd25",
            "score": 5,
            "author": "KDNeedsMoreHelp"
        },
        {
            "level": 0,
            "comment": "Asta and yami vs one of the spade kingdom, forget which one.",
            "score": 3,
            "author": "Dry-Smoke6528",
            "replies": [
                {
                    "level": 1,
                    "comment": "Dante, and HELL YES.",
                    "score": 2,
                    "author": "88Dubs",
                    "replies": [
                        {
                            "level": 2,
                            "comment": "Easily my favorite fight for the series so far",
                            "score": 2,
                            "author": "Dry-Smoke6528"
                        }
                    ]
                }
            ]
        },
        {
            "level": 0,
            "comment": "For its time, Kenshin vs Saito in Rurouni Kenshin is phenomenally done and still holds up today",
            "score": 4,
            "author": "mayekchris",
            "replies": [
                {
                    "level": 1,
                    "comment": "That's one of the things I can't wait to see done in the remake. It wasn't like kenshin vs shishio where you had a bunch of weird circles popping up whenever he did a special attack.",
                    "score": 1,
                    "author": "DarkDan3",
                    "replies": [
                        {
                            "level": 2,
                            "comment": "That's because two of the three Shishio fight episodes had bad animation in comparison to the climax",
                            "score": 3,
                            "author": "mayekchris"
                        }
                    ]
                }
            ]
        },
        {
            "level": 0,
            "comment": "Fate/Zero has a whole has an excellent dub but Kirei vs Kiritusgu is one of my all time favorite fights",
            "score": 8,
            "author": "J3wFro8332"
        },
        {
            "level": 0,
            "comment": "Basically any fate fight from unlimited blade works and heavens feel. Zero has some good ones but not as many and some other date projects that weren\u2019t animated by ufotable have good fights but not as many or as high of quality.",
            "score": 3,
            "author": "Biggyboi553",
            "replies": [
                {
                    "level": 1,
                    "comment": "Sieg vs Karna in Apocrypha is excellent.  So is Achilles vs Chiron in the same one.  Personally, I think Apocrypha has some of the best fights.",
                    "score": 5,
                    "author": "DemonSlyr007",
                    "replies": [
                        {
                            "level": 2,
                            "comment": "I agree think they have some great fights too but definitely not as good as others from ufotable.",
                            "score": 1,
                            "author": "Biggyboi553"
                        },
                        {
                            "level": 2,
                            "comment": "Anything with karna was so cool",
                            "score": 1,
                            "author": "neverforgetbillymays"
                        }
                    ]
                }
            ]
        },
        {
            "level": 0,
            "comment": "Fate Heavens Feel, Eminence in Shadow, Black Clover",
            "score": 3,
            "author": "massio1"
        },
        {
            "level": 0,
            "comment": "Demon slayer and also fire force has some bangers",
            "score": 3,
            "author": "kaitezzz"
        },
        {
            "level": 0,
            "comment": "It doesn't get talked about much anymore, but you should track down a film called [Sword of the Stranger](https://myanimelist.net/anime/2418/Stranger__Mukou_Hadan?q=sword%20of%20the%20stranger&amp;cat=anime). It has extremely impressive animation and fight choreography.",
            "score": 3,
            "author": "Zer0nyx"
        },
        {
            "level": 0,
            "comment": "HunterXHunter Kurapika vs Uvogin\n\nGyutaro vs tengen - demon slayer\n\nTanjiro vs rui - demon slayer\n\nNaruto vs pain \n\nGoku vs hit\n\nLuffy vs lucci \n\nJust to name a few",
            "score": 3,
            "author": "Kpet1010"
        },
        {
            "level": 0,
            "comment": "Sword Art Online - particularly the War of Underworld arc, which has one amazing fight scene after another. Attack on Titan also has some fantastic battles, whether it's humans vs titans, titans vs titans or humans vs humans.",
            "score": 4,
            "author": "Heda-of-Aincrad"
        },
        {
            "level": 0,
            "comment": "Rill is the rill dill.",
            "score": 2,
            "author": "mab0390"
        },
        {
            "level": 0,
            "comment": "Finale of S-Cry-Ed",
            "score": 2,
            "author": "Sturdevant",
            "replies": [
                {
                    "level": 1,
                    "comment": "Favorite part of the whole show",
                    "score": 1,
                    "author": "firehahahahahaha"
                }
            ]
        },
        {
            "level": 0,
            "comment": "Basically any fight from Gurren Lagann",
            "score": 2,
            "author": "Dinkleballs"
        },
        {
            "level": 0,
            "comment": "Exia vs 0 Gundam",
            "score": 2,
            "author": "Yakuza-wolf_kiwami"
        },
        {
            "level": 0,
            "comment": "Hellsing Ultimate, I personally really liked Alucard vs The Dandy Man, but all of them are good",
            "score": 2,
            "author": "FrostBalrog"
        },
        {
            "level": 0,
            "comment": "Garfiel against Elsa in Re Zero season 2 is one of my favorites",
            "score": 2,
            "author": "Majora101"
        },
        {
            "level": 0,
            "comment": "Tengen vs Gyutaro was amazing, but my favourite is still Rengoku vs Akaza, love the soundtrack in that one so much",
            "score": 2,
            "author": "Xthe_tallest_one"
        },
        {
            "level": 0,
            "comment": "Naruto vs Sasuke, kakashi vs Obito, Yamamoto vs ywach, deku vs todoroki Madara vs the entire allied Shinobi forces",
            "score": 5,
            "author": "MaG4436"
        },
        {
            "level": 0,
            "comment": "They're not fights except in the most loosest of senses, but I always remember the matches in Hanebado because they were rotoscoped and looked amazingly smooth and natural.",
            "score": 4,
            "author": "SoundOf1HandClapping"
        },
        {
            "level": 0,
            "comment": "Goku vs perfect cell.",
            "score": 2,
            "author": "Dinobrony318"
        },
        {
            "level": 0,
            "comment": "The fire spear guy vs the main character in Fate apothica holy shit unreal. Also great sound design",
            "score": 1,
            "author": "Popular_Mode_6453"
        },
        {
            "level": 0,
            "comment": "Homura vs Mami in PMMM Rebellion is my favorite for both the animation itself but also the twists and turns.",
            "score": 1,
            "author": "DenizenOfZen"
        },
        {
            "level": 0,
            "comment": "Yusuke Urameshi vs Chu\n\nKurama v elder toguro \n\nthe whole dark tournament tbh",
            "score": 1,
            "author": "TheMidnightApostle"
        },
        {
            "level": 0,
            "comment": "Gundam 00 vs Bushido",
            "score": 1,
            "author": "Popular_Mode_6453"
        },
        {
            "level": 0,
            "comment": "Surprised no one has mentioned the entire back half of Dragon Ball Super: Broly, but especially [the last fight in the movie](https://www.youtube.com/watch?v=sm92AV0Mhkg). I described the movie as \"how we remember Dragon Ball as kids.\" I was bummed Super Hero went the CGI route despite it looking very good as well.",
            "score": 1,
            "author": "KyledKat"
        },
        {
            "level": 0,
            "comment": "Last episode of s1 of Daily Life of the Immortal King, when an OP MC rages out with no restraints. It\u2019s peak. You also get the OP playing during the scene. https://m.youtube.com/watch?v=6Q9dMKCTowg&amp;pp=ygUnRGFpbHkgbGlmZSBpbW1vcnRhbCBraW5nIHdhbmcgbGluZyByYWdl\n\n\nThis isn\u2019t the dub but still",
            "score": 1,
            "author": "MattScoot"
        },
        {
            "level": 0,
            "comment": "Honestly, I never cared about fight scenes. But I do appreciate character moments.\n\nSo, if I had to claim one, watching Geld beat down Shogo in Slime was therapeutic.",
            "score": -3,
            "author": "Filty-Cheese-Steak"
        }
    ]
}