{
    "id": "13ll41z",
    "score": 2,
    "title": "Grad tickets for May 22 @12",
    "author": "No_Psychology1070",
    "date": 1684471136.0,
    "url": "https://www.reddit.com/r/CalPolyPomona/comments/13ll41z",
    "media_urls": [],
    "other_urls": [],
    "postText": "Does anyone have extra tickets for May 22nd at 12? Willing to pay for them!",
    "comments": [
        {
            "level": 0,
            "comment": "I have 1 extra",
            "score": 1,
            "author": "TechnologyGlobal3880",
            "replies": [
                {
                    "level": 1,
                    "comment": "hiii, can I dm you on something!! if you still have that extra for 8am",
                    "score": 1,
                    "author": "fatherlyfrankie"
                }
            ]
        },
        {
            "level": 0,
            "comment": "How many tickets are you allowed? I graduate next year",
            "score": 0,
            "author": "djwoodie98",
            "replies": [
                {
                    "level": 1,
                    "comment": "This year, they gave 8 tickets. And if there were extra, they made an announcement but each department/college is different. For CLASS, they gave us 3 extra so in total 11 tickets. Could be different next year.",
                    "score": 1,
                    "author": "blxncitx"
                }
            ]
        }
    ]
}